HISTORY.md
MANIFEST.in
README.md
pyproject.toml
setup.py
environment/requirements.txt
src/projectoneflow.egg-info/PKG-INFO
src/projectoneflow.egg-info/SOURCES.txt
src/projectoneflow.egg-info/dependency_links.txt
src/projectoneflow.egg-info/entry_points.txt
src/projectoneflow.egg-info/requires.txt
src/projectoneflow.egg-info/top_level.txt
src/projectoneflow/core/__init__.py
src/projectoneflow/core/types.py
src/projectoneflow/core/cli/__init__.py
src/projectoneflow/core/cli/cli.py
src/projectoneflow/core/deploy/__init__.py
src/projectoneflow/core/deploy/cli.py
src/projectoneflow/core/deploy/terraform/__init__.py
src/projectoneflow/core/deploy/terraform/cli.py
src/projectoneflow/core/deploy/terraform/databricks.py
src/projectoneflow/core/event/__init__.py
src/projectoneflow/core/event/manager.py
src/projectoneflow/core/exception/__init__.py
src/projectoneflow/core/exception/deploy.py
src/projectoneflow/core/exception/execution.py
src/projectoneflow/core/exception/sources.py
src/projectoneflow/core/exception/validation.py
src/projectoneflow/core/execution/__init__.py
src/projectoneflow/core/execution/write.py
src/projectoneflow/core/execution/operator/__init__.py
src/projectoneflow/core/execution/operator/spark_task/__init__.py
src/projectoneflow/core/execution/operator/spark_task/execution.py
src/projectoneflow/core/execution/operator/spark_task/input.py
src/projectoneflow/core/execution/operator/spark_task/output.py
src/projectoneflow/core/execution/spark_task/__init__.py
src/projectoneflow/core/execution/spark_task/context.py
src/projectoneflow/core/execution/spark_task/execution_fn.py
src/projectoneflow/core/observability/__init__.py
src/projectoneflow/core/observability/datalogger.py
src/projectoneflow/core/observability/logging.py
src/projectoneflow/core/observability/spark_listener.py
src/projectoneflow/core/runtime/__init__.py
src/projectoneflow/core/schemas/__init__.py
src/projectoneflow/core/schemas/data_objects.py
src/projectoneflow/core/schemas/deploy.py
src/projectoneflow/core/schemas/event.py
src/projectoneflow/core/schemas/execution.py
src/projectoneflow/core/schemas/features.py
src/projectoneflow/core/schemas/input.py
src/projectoneflow/core/schemas/output.py
src/projectoneflow/core/schemas/refresh.py
