Metadata-Version: 2.4
Name: projectoneflow
Version: 1.0.0
Summary: This Project is data engineering framework which implements all data engineering ingestion patterns
Author-email: Mukhesh Narra <narramukhesh@gmail.com>
Maintainer-email: Mukhesh Narra <narramukhesh@gmail.com>
License-Expression: MIT
Project-URL: bugs, https://github.com/narramukhesh/projectone/issues
Project-URL: changelog, https://github.com/narramukhesh/projectone/tree/main/projectoneflow/HISTORY.md
Project-URL: homepage, https://github.com/narramukhesh/projectone/tree/main/projectoneflow
Keywords: dataengineering,projectoneflow,pyspark,delta-lake,Python
Classifier: Development Status :: 5 - Production/Stable
Classifier: Natural Language :: English
Classifier: Intended Audience :: Developers
Classifier: Topic :: Software Development
Requires-Python: >=3.10
Requires-Dist: pip==24.1.2
Requires-Dist: pydantic==2.9.2
Requires-Dist: pyarrow==17.0.0
Requires-Dist: pre_commit==4.0.0
Requires-Dist: pandas==2.2.2
Requires-Dist: delta-spark==3.2.0
Requires-Dist: pytest==8.3.3
Requires-Dist: Sphinx==7.2.6
Requires-Dist: openpyxl==3.1.2
Requires-Dist: black==24.10.0
Requires-Dist: numpy==1.26.3
Requires-Dist: colorlog==6.8.2
Requires-Dist: confluent-kafka==2.6.0
Requires-Dist: pytest-cov==5.0.0
Requires-Dist: requests==2.32.3
Requires-Dist: cdktf==0.20.9
Requires-Dist: cdktf-cdktf-provider-databricks==13.30.0
Requires-Dist: build==0.9.0
Requires-Dist: Office365-REST-Python-Client==2.5.13
Requires-Dist: openpyxl==3.1.2
Requires-Dist: paramiko==3.5.0
